input_generator/__init__.py
input_generator/checker.py
input_generator-0.0.0.dist-info/METADATA
input_generator-0.0.0.dist-info/WHEEL
input_generator-0.0.0.dist-info/top_level.txt
input_generator-0.0.0.dist-info/RECORD
