Metadata-Version: 2.1
Name: input-generator
Version: 0.0.0
Summary: input_generator package
Home-page: UNKNOWN
License: MIT
Platform: UNKNOWN
Classifier: License :: OSI Approved :: MIT License
Classifier: Programming Language :: Python :: 3
Classifier: Programming Language :: Python :: 3.7
